.gitignore
MANIFEST.in
README.rst
bootstrap.py
buildout.cfg
collective.footerportletmanager-configure.zcml
setup.py
collective/__init__.py
collective.footerportletmanager.egg-info/PKG-INFO
collective.footerportletmanager.egg-info/SOURCES.txt
collective.footerportletmanager.egg-info/dependency_links.txt
collective.footerportletmanager.egg-info/entry_points.txt
collective.footerportletmanager.egg-info/namespace_packages.txt
collective.footerportletmanager.egg-info/not-zip-safe
collective.footerportletmanager.egg-info/requires.txt
collective.footerportletmanager.egg-info/top_level.txt
collective/footerportletmanager/__init__.py
collective/footerportletmanager/configure.zcml
collective/footerportletmanager/footer_manageportlets.pt
collective/footerportletmanager/footer_renderer.pt
collective/footerportletmanager/footer_viewlet_portlets.pt
collective/footerportletmanager/layer.py
collective/footerportletmanager/portletmanager.py
collective/footerportletmanager/rebuild_i18n.sh
collective/footerportletmanager/testing.py
collective/footerportletmanager/upgrades.py
collective/footerportletmanager/upgrades.zcml
collective/footerportletmanager/locales/collective.footerportletmanager.pot
collective/footerportletmanager/locales/en/LC_MESSAGES/collective.footerportletmanager.po
collective/footerportletmanager/locales/fr/LC_MESSAGES/collective.footerportletmanager.po
collective/footerportletmanager/profiles/default/browserlayer.xml
collective/footerportletmanager/profiles/default/controlpanel.xml
collective/footerportletmanager/profiles/default/metadata.xml
collective/footerportletmanager/profiles/default/portlets.xml
collective/footerportletmanager/tests/__init__.py
collective/footerportletmanager/tests/base.py
collective/footerportletmanager/tests/test_setup.py
docs/HISTORY.txt