Metadata-Version: 1.0
Name: collective.footerportletmanager
Version: 1.0
Summary: Footer portlet manager for Plone
Home-page: https://github.com/collective/collective.footerportletmanager
Author: JeanMichel FRANCOIS aka toutpt
Author-email: toutpt@gmail.com
License: GPL
Keywords: plone portlet
Platform: UNKNOWN
Classifier: Programming Language :: Python
Classifier: Framework :: Plone
Classifier: Framework :: Plone :: 4.0
Classifier: Framework :: Plone :: 4.1
Classifier: Framework :: Plone :: 4.2
